LICENSE
MANIFEST.in
README.md
setup.py
django_cool_pagination.egg-info/PKG-INFO
django_cool_pagination.egg-info/SOURCES.txt
django_cool_pagination.egg-info/dependency_links.txt
django_cool_pagination.egg-info/top_level.txt
django_cool_paginator/__init__.py
django_cool_paginator/exceptions/__init__.py
django_cool_paginator/exceptions/tag_exceptions.py
django_cool_paginator/templates/__paginator.html
django_cool_paginator/templatetags/__init__.py
django_cool_paginator/templatetags/cool_paginate.py
django_cool_paginator/templatetags/paginator_tags.py
tests/__init__.py
tests/test_settings.py
tests/tests.py