Metadata-Version: 1.1
Name: django-cool-pagination
Version: 0.2.2
Summary: Simple pagination app that saves your time.
Home-page: https://github.com/joe513/django-cool-pagination
Author: Jabrail Lezgintsev
Author-email: lezgintsev13@yandex.ru
License: MIT License
Keywords: python,django,pagination
Platform: UNKNOWN
Classifier: Environment :: Web Environment
Classifier: Framework :: Django
Classifier: Framework :: Django :: 2.0
Classifier: Intended Audience :: Developers
Classifier: License :: OSI Approved :: MIT License
Classifier: Operating System :: OS Independent
Classifier: Programming Language :: Python
Classifier: Programming Language :: Python :: 3.6
Classifier: Programming Language :: Python :: 3.5
Classifier: Programming Language :: Python :: 3.4
Classifier: Topic :: Internet :: WWW/HTTP
Classifier: Topic :: Internet :: WWW/HTTP :: Dynamic Content
